{
  "title": "Neznámý titulek",
  "url": "https://www.bjjee.com/bjj-news/santa-cruz-medicinals-founder-explains-why-bjj-is-better-than-striking-martial-arts/",
  "date": null,
  "author": null,
  "content": ". . NEWS BJJ ARTICLES SHOP CONTACT CONTRIBUTE AN ARTICLE PRIVACY POLICY HomeArticlesBJJ NewsSanta Cruz Medicinals Founder Explains Why BJJ Is Better Than Striking Martial Arts Santa Cruz Medicinals Founder Explains Why BJJ Is Better Than Striking Martial Arts APR 11, 2026BJJEE1 AdminArticles, BJJ News Brendan Ruh, founder of Santa Cruz Medicinals, recently shared his perspective on training, injuries, and martial arts. Ruh outlined a balanced but demanding weekly routine of his own: My training regimen is I do weights like hard like three times a week. And then I try to go to jiu-jitsu like twice a week. And then I surf. He also pointed to the physical demands of grappling: People in jiu-jitsu, 1,000 calorie days. It’s hard work… I’m in the leg lock game now. Like my stuff’s always tweaked, dude. I always have a little tweak. Knee issues, particularly from heel hooks, have become a recurring challenge. But he offered some perspective for those newer to the sport: You get less injured once you reach this sort of level. Like maybe like blue belt and above… You’ll start to know what’s good. Despite that, he believes grappling remains safer than striking in the long run: The cool thing about jiu-jitsu is I’ll go train with Michael Morales, and it’s like I’m going to get messed up, but I’m going to be fine. By contrast, he noted that striking carries a different kind of risk: I do think jiu-jitsu and wrestling are better than striking martial arts. You go to a boxing class, now you’re sparring. And the only way to actually get better at that sport is spar hard. You’re going to get hit in the head. For the average person, his conclusion is straightforward: For just like the normal person who wants to do martial arts defending themselves, I think jiu-jitsu is the best. Sloth Jiu-Jitsu: The Ultimate Guide for Calmly Beating Bigger, Younger Opponents 💥 What if slowing down was the fastest way to win? 💭 Tired of Getting Smashed by Younger, Stronger Grapplers? It’s not your age. It’s your strategy. If you’re a passionate grappler over 35 who’s sick of getting outpaced, outmuscled, or out-cardio’d by opponents half your age — this 120 page e-book was made for you. 🔓 Unlock the Power of Sloth Jiu-Jitsu: Build Sustainable Strength—Without Wrecking Your Joints, Energy, or Jiu-Jitsu Tired of waking up sore and burnt out after lifting? Sloth Strength is a proven blueprint for grapplers over 35 who want to get stronger—without the pain, burnout, or injuries. Developed from 25 years on the mats, this no-burnout approach is made specifically for BJJ athletes in their 30s, 40s, and beyond. boxing Brendan Ruh striking Share Save RELATED ARTICLES Sydney Sweeney Hints At Fighting In A Real Boxing Match: “I Love Fighting” Cro Cop Confirms Match With Fedor Emelianenko: “I Signed Back In February” (WATCH) Wanderlei Silva Knocked Out In Crazy Post-Fight Brawl Grandson Of Muhammad Ali – Biaggio Ali Walsh – Choked Unconscious At PFL 7 By Ronnie Gibbs RECENT POSTS Santa Cruz Medicinals Founder Explains Why BJJ Is Better Than Striking Martial Arts APR 11, 2026BJJEE1 Admin Marcus “Buchecha” Almeida vs. Max Gimenis Set For UFC Vegas 116 APR 10, 2026BJJEE1 Admin (WATCH) BJJ Instructor Demotes Student From Brown To Blue Belt APR 10, 2026BJJEE1 Admin Jocko Willink: “The Best Jiu-Jitsu Gym Is The Closest One” APR 09, 2026BJJEE1 Admin Kade Ruotolo Faces Toughest MMA Test Yet Against Hiroyuki Tetsuka at ONE: The Inner Circle APR 09, 2026BJJEE1 Admin Dante Leon Eyes Redemption: “I Have To Show Up & Be Better” APR 08, 2026BJJEE1 Admin Arman Tsarukyan: “I’m More Well-Rounded Than Prime Khabib” APR 08, 2026BJJEE1 Admin UFC BJJ 8: Mikey Musumeci To Defend UFC BJJ Title Against Kevin Dantzler APR 07, 2026BJJEE1 Admin (WATCH) Izaak Michell Confronted On Live TV Amid Arrest Warrant APR 07, 2026BJJEE1 Admin Jiri Prochazka Explains His Extreme Training: “It’s About Facing Fear” APR 06, 2026BJJEE1 Admin CATEGORIES Articles BJJ Belt ranking BJJ News BJJEE Podcast Competition Preview Competitions/Tournaments Contests Featured Gear review Health Health & Nutrition Interview Interviews Nutrition Regional BJJ News Seminar Strength & Conditioning Training report Uncategorized Videos Login © Bjj Eastern Europe 2012. All rights reserved. Website setup Cosbus.dk"
}